{
  "rest": {
    "server" : {
      "port": 8080
    },
    "authentication": {
      "username": {
        "password": "password"
      }
    }
  },
  "buildtools": {
    "run": false,
    "path": "files/BuildTools/",
    "FileName": "Build.jar"
  },
  "minecraftserv": {
    "path": "files/MinecraftServer/",
    "FileName": "server.jar",
    "minRam": "2G",
    "maxRam": "4G",
    "AutoRestart": false,
    "AutoStart": true,
    "worldsDir": "../worlds/",
    "pluginsDir": "../plugins/",
    "configDirectory": "../settings/"
  }
}